__init__.py
authnexus-0.1.1.dist-info/licenses/LICENSE
core/auth_manager.py
core/security_monitor.py
core/webauthn.py
integerations/fastapi.py
integerations/flask.py
authnexus-0.1.1.dist-info/METADATA
authnexus-0.1.1.dist-info/WHEEL
authnexus-0.1.1.dist-info/entry_points.txt
authnexus-0.1.1.dist-info/top_level.txt
authnexus-0.1.1.dist-info/RECORD
