Metadata-Version: 2.4
Name: authnexus
Version: 0.1.1
Summary: Enterprise-Grade Authentication Framework with Modern Security Protocols
Author-email: Satwik Mishra <satwikmishra46@gmail.com>
License: AGPL-3.0
Project-URL: Homepage, https://github.com/satwikmishra11/authnexus
Project-URL: Documentation, https://authnexus.readthedocs.io
Project-URL: Changelog, https://github.com/satwikmishra11/authnexus/releases
Project-URL: Issues, https://github.com/satwikmishra11/authnexus/issues
Keywords: authentication,security,webauthn,oauth,jwt
Classifier: License :: OSI Approved :: GNU Affero General Public License v3
Classifier: Programming Language :: Python :: 3
Classifier: Programming Language :: Python :: 3.8
Classifier: Programming Language :: Python :: 3.9
Classifier: Programming Language :: Python :: 3.10
Classifier: Programming Language :: Python :: 3.11
Classifier: Topic :: Security
Classifier: Topic :: Software Development :: Libraries
Classifier: Intended Audience :: Developers
Classifier: Intended Audience :: System Administrators
Classifier: Framework :: FastAPI
Classifier: Framework :: Flask
Requires-Python: >=3.8
License-File: LICENSE
Requires-Dist: cryptography>=42.0
Requires-Dist: python-jose[cryptography]>=3.3
Requires-Dist: webauthn>=1.2.0
Requires-Dist: pydantic>=2.0
Requires-Dist: httpx>=0.24
Requires-Dist: typing-extensions>=4.0
Provides-Extra: security
Requires-Dist: bandit>=1.7; extra == "security"
Requires-Dist: safety>=2.3; extra == "security"
Requires-Dist: semgrep>=1.0; extra == "security"
Provides-Extra: dev
Requires-Dist: pytest>=7.0; extra == "dev"
Requires-Dist: pytest-cov>=4.0; extra == "dev"
Requires-Dist: ruff>=0.0.28; extra == "dev"
Requires-Dist: mypy>=1.0; extra == "dev"
Requires-Dist: build>=0.10; extra == "dev"
Dynamic: license-file
